beastcp/__init__.py
beastcp/cli.py
beastcp-1.0.2.dist-info/METADATA
beastcp-1.0.2.dist-info/WHEEL
beastcp-1.0.2.dist-info/entry_points.txt
beastcp-1.0.2.dist-info/top_level.txt
beastcp-1.0.2.dist-info/RECORD
