Metadata-Version: 2.4
Name: beastcp
Version: 1.0.2
Summary: A high-performance cp-like file copier with resume, verification, tqdm progress, and multi-threaded directory sync.
Author-email: Utkarsh Pathak <utkarshpathak16@gmail.com>
Requires-Python: >=3.8
Requires-Dist: tqdm
Requires-Dist: click
